azure/mgmt/recoveryservicessiterecovery/__init__.py
azure/mgmt/recoveryservicessiterecovery/_configuration.py
azure/mgmt/recoveryservicessiterecovery/_patch.py
azure/mgmt/recoveryservicessiterecovery/_serialization.py
azure/mgmt/recoveryservicessiterecovery/_site_recovery_management_client.py
azure/mgmt/recoveryservicessiterecovery/_version.py
azure/mgmt/recoveryservicessiterecovery/py.typed
azure/mgmt/recoveryservicessiterecovery/aio/__init__.py
azure/mgmt/recoveryservicessiterecovery/aio/_configuration.py
azure/mgmt/recoveryservicessiterecovery/aio/_patch.py
azure/mgmt/recoveryservicessiterecovery/aio/_site_recovery_management_client.py
azure/mgmt/recoveryservicessiterecovery/aio/operations/__init__.py
azure/mgmt/recoveryservicessiterecovery/aio/operations/_cluster_recovery_point_operations.py
azure/mgmt/recoveryservicessiterecovery/aio/operations/_cluster_recovery_points_operations.py
azure/mgmt/recoveryservicessiterecovery/aio/operations/_migration_recovery_points_operations.py
azure/mgmt/recoveryservicessiterecovery/aio/operations/_operations.py
azure/mgmt/recoveryservicessiterecovery/aio/operations/_patch.py
azure/mgmt/recoveryservicessiterecovery/aio/operations/_recovery_points_operations.py
azure/mgmt/recoveryservicessiterecovery/aio/operations/_replication_alert_settings_operations.py
azure/mgmt/recoveryservicessiterecovery/aio/operations/_replication_appliances_operations.py
azure/mgmt/recoveryservicessiterecovery/aio/operations/_replication_eligibility_results_operations.py
azure/mgmt/recoveryservicessiterecovery/aio/operations/_replication_events_operations.py
azure/mgmt/recoveryservicessiterecovery/aio/operations/_replication_fabrics_operations.py
azure/mgmt/recoveryservicessiterecovery/aio/operations/_replication_jobs_operations.py
azure/mgmt/recoveryservicessiterecovery/aio/operations/_replication_logical_networks_operations.py
azure/mgmt/recoveryservicessiterecovery/aio/operations/_replication_migration_items_operations.py
azure_mgmt_recoveryservicessiterecovery-1.3.0.dist-info/LICENSE
azure_mgmt_recoveryservicessiterecovery-1.3.0.dist-info/METADATA
azure_mgmt_recoveryservicessiterecovery-1.3.0.dist-info/WHEEL
azure_mgmt_recoveryservicessiterecovery-1.3.0.dist-info/top_level.txt
azure_mgmt_recoveryservicessiterecovery-1.3.0.dist-info/RECORD
